{"provider":"google","id":"112913453950459476449","displayName":"John Giffin","name":{"familyName":"Giffin","givenName":"John"},"emails":[{"value":"infinitehoax@gmail.com"}],"_raw":"{\n \"id\": \"112913453950459476449\",\n \"email\": \"infinitehoax@gmail.com\",\n \"verified_email\": true,\n \"name\": \"John Giffin\",\n \"given_name\": \"John\",\n \"family_name\": \"Giffin\",\n \"link\": \"https://plus.google.com/112913453950459476449\",\n \"gender\": \"male\",\n \"birthday\": \"0000-02-02\",\n \"locale\": \"en\"\n}\n","_json":{"id":"112913453950459476449","email":"infinitehoax@gmail.com","verified_email":true,"name":"John Giffin","given_name":"John","family_name":"Giffin","link":"https://plus.google.com/112913453950459476449","gender":"male","birthday":"0000-02-02","locale":"en"}}
